germail
